{
  "index": {
    "title": "Home",
    "theme": {
      "layout": "full",
      "breadcrumb": false,
      "footer": true,
      "sidebar": false,
      "toc": false,
      "pagination": false
    }
  },
  "getting-started": {
    "title": "Getting Started",
    "theme": {
      "breadcrumb": false
    }
  },
  "api-reference": {
    "title": "API Reference",
    "theme": {
      "breadcrumb": false
    }
  },
  "changelog": {
    "title": "Release Notes",
    "type": "page",
    "href": "https://github.com/chengpeiquan/react-forage/blob/main/CHANGELOG.md",
    "newWindow": true
  },
  "localforage-api": {
    "title": "LocalForage API",
    "type": "page",
    "href": "https://localforage.github.io/localForage/",
    "newWindow": true
  }
}